[
    {
        "offset": 933,
        "size": 36,
        "name_offset": 901,
        "name": "【碧】",
        "jp": "「ハァ、ハァ、ハァ……」",
        "text": "「哈啊，哈啊，哈啊……」"
    },
    {
        "offset": 1488,
        "size": 75,
        "name_offset": 0,
        "name": "",
        "jp": "風車が建ち並ぶ丘を、ロードバイクで駆け抜けていく。",
        "text": "骑着公路自行车，穿过风车林立的山丘。"
    },
    {
        "offset": 1721,
        "size": 126,
        "name_offset": 0,
        "name": "",
        "jp": "斜面を昇ってくる風が、玉の汗を滴らせる身体を冷まし、故郷へ向かう背中を押してくれる。",
        "text": "风从山坡上吹来，吹凉了我滴着汗珠的身体，推着我的后背走向故乡。"
    },
    {
        "offset": 3065,
        "size": 33,
        "name_offset": 0,
        "name": "",
        "jp": "懐かしい、風ヶ浦の風。",
        "text": "让人怀念的，风浦的风。"
    },
    {
        "offset": 3429,
        "size": 93,
        "name_offset": 0,
        "name": "",
        "jp": "東京で就職してから数ヶ月。夏休みを貰って、初めての帰郷だった。",
        "text": "我在东京工作已经几个月了。趁着暑假，这是我第一次回乡。"
    },
    {
        "offset": 3680,
        "size": 51,
        "name_offset": 0,
        "name": "",
        "jp": "せっかくだから自転車で帰ってきた。",
        "text": "机会难得，我骑着自行车回来。"
    },
    {
        "offset": 4654,
        "size": 45,
        "name_offset": 4622,
        "name": "【碧】",
        "jp": "「ここの風を感じたかったんだ」",
        "text": "「以前我就想感受一下这里的风了」"
    },
    {
        "offset": 5472,
        "size": 99,
        "name_offset": 0,
        "name": "",
        "jp": "風車の丘に吹く風はとくに気持ちいい。空で感じるほどではないけれど。",
        "text": "风车之丘上吹的风让人感觉很舒服。虽然比不上天空中那么惬意。"
    },
    {
        "offset": 6702,
        "size": 63,
        "name_offset": 0,
        "name": "",
        "jp": "丘を通り抜けて湖を回り込み、市街地に入る。",
        "text": "穿过山丘，绕过湖泊，进入了市区。"
    },
    {
        "offset": 7228,
        "size": 66,
        "name_offset": 0,
        "name": "",
        "jp": "もうしばらく走ると、古びた洋館が見えてきた。",
        "text": "再往前骑了一会，一栋西式的老房子出现在了眼前。"
    },
    {
        "offset": 8080,
        "size": 69,
        "name_offset": 0,
        "name": "",
        "jp": "トビウオ荘。恵風学園に通う生徒のための学生寮。",
        "text": "飞鱼庄。给惠风学园的学生使用的宿舍。"
    },
    {
        "offset": 8554,
        "size": 33,
        "name_offset": 8522,
        "name": "【碧】",
        "jp": "「変わってないな……」",
        "text": "「什么也没变啊……」"
    },
    {
        "offset": 8745,
        "size": 66,
        "name_offset": 0,
        "name": "",
        "jp": "一年前まで、この“女子寮”で寮母をしていた。",
        "text": "直到一年前，我还是这个“女生宿舍”的宿管。"
    },
    {
        "offset": 8969,
        "size": 102,
        "name_offset": 0,
        "name": "",
        "jp": "男子生徒である俺が、女子寮で寮母というのは、今思うと無茶苦茶な話だ。",
        "text": "现在想想，作为男学生的我，当女生宿舍的宿管，真是荒唐。"
    },
    {
        "offset": 9229,
        "size": 90,
        "name_offset": 0,
        "name": "",
        "jp": "それ故の苦労もあったけど、ここで暮らした日々は充実していた。",
        "text": "虽然因此经历了一些困难，但我在这里度过的每一天都很充实。"
    },
    {
        "offset": 9477,
        "size": 42,
        "name_offset": 0,
        "name": "",
        "jp": "色んな思い出が詰まった場所。",
        "text": "这是个充满各种回忆的地方。"
    },
    {
        "offset": 9677,
        "size": 51,
        "name_offset": 0,
        "name": "",
        "jp": "今日はここで懐かしいメンバーが――",
        "text": "今天要在这与怀念的同伴们——"
    },
    {
        "offset": 9954,
        "size": 18,
        "name_offset": 9922,
        "name": "【碧】",
        "jp": "「……ん？」",
        "text": "「……嗯？」"
    },
    {
        "offset": 10434,
        "size": 36,
        "name_offset": 10396,
        "name": "【ハット】",
        "jp": "「クワッ……クワッ……」",
        "text": "「呱啊……呱啊……」"
    },
    {
        "offset": 10671,
        "size": 15,
        "name_offset": 10639,
        "name": "【碧】",
        "jp": "「ハット」",
        "text": "「哈特」"
    },
    {
        "offset": 10994,
        "size": 15,
        "name_offset": 10956,
        "name": "【ハット】",
        "jp": "「クワ？」",
        "text": "「呱？」"
    },
    {
        "offset": 11686,
        "size": 21,
        "name_offset": 11648,
        "name": "【ハット】",
        "jp": "「ガァガァ！」",
        "text": "「嘎嘎！」"
    },
    {
        "offset": 11865,
        "size": 90,
        "name_offset": 0,
        "name": "",
        "jp": "さっそく再会した懐かしい友人が、翼をひろげて飛び込んできた。",
        "text": "很快重逢的老朋友，张开翅膀飞了过来。"
    },
    {
        "offset": 12156,
        "size": 60,
        "name_offset": 12124,
        "name": "【碧】",
        "jp": "「ハット、久しぶりだな。元気だったか？」",
        "text": "「哈特，好久不见了。你还好吗？」"
    },
    {
        "offset": 12565,
        "size": 33,
        "name_offset": 12527,
        "name": "【ハット】",
        "jp": "「グワッ！　グワッ！」",
        "text": "「呱啊！ 呱啊！」"
    },
    {
        "offset": 12799,
        "size": 36,
        "name_offset": 12767,
        "name": "【碧】",
        "jp": "「ははは、そうかそうか」",
        "text": "「哈哈哈，这样啊」"
    },
    {
        "offset": 13342,
        "size": 139,
        "name_offset": 0,
        "name": "",
        "jp": "今日はここ――トビウオ荘で、懐かしいメンバーが集まって、休暇を過ごす予定だった。",
        "text": "今天在这里——在飞鱼庄，让人怀念的同伴们打算要聚在一起度假。"
    }
]
